mcp_test_2/__init__.py
mcp_test_2/server.py
mcp_test_2-1.0.2.dist-info/WHEEL
mcp_test_2-1.0.2.dist-info/entry_points.txt
mcp_test_2-1.0.2.dist-info/METADATA
mcp_test_2-1.0.2.dist-info/RECORD
