Metadata-Version: 2.3
Name: mcp-test-2
Version: 1.0.2
Summary: Add your description here
Requires-Dist: alibabacloud-ram20150501>=1.2.0
Requires-Dist: bs4>=0.0.2
Requires-Dist: dashscope>=1.24.0
Requires-Dist: dotenv>=0.9.9
Requires-Dist: httpx>=0.28.1
Requires-Dist: mcp[cli]>=1.12.2
Requires-Python: >=3.13
